Metadata-Version: 2.1
Name: odoo14-addon-purchase-request-cancel-confirm
Version: 14.0.1.0.1
Summary: Purchase Request Cancel Confirm
Home-page: https://github.com/OCA/purchase-workflow
Author: Ecosoft,Odoo Community Association (OCA)
Author-email: support@odoo-community.org
License: AGPL-3
Platform: UNKNOWN
Classifier: Programming Language :: Python
Classifier: Framework :: Odoo
Classifier: Framework :: Odoo :: 14.0
Classifier: License :: OSI Approved :: GNU Affero General Public License v3
Requires-Python: >=3.6
Requires-Dist: odoo14-addon-base-cancel-confirm
Requires-Dist: odoo14-addon-purchase-request
Requires-Dist: odoo (<14.1dev,>=14.0a)
